MANIFEST.in
README.md
setup.py
random_custom_pdf/__init__.py
random_custom_pdf/random.py
random_custom_pdf/requirements.txt
random_custom_pdf.egg-info/PKG-INFO
random_custom_pdf.egg-info/SOURCES.txt
random_custom_pdf.egg-info/dependency_links.txt
random_custom_pdf.egg-info/requires.txt
random_custom_pdf.egg-info/top_level.txt