Metadata-Version: 1.1
Name: random-custom-pdf
Version: 0.0.2
Summary: numpy based random generator with custom probability distribution function
Home-page: https://github.com/kapot65/random_custom_pdf
Author: Vasiliy Chernov
Author-email: kapot65@gmail.com
License: UNKNOWN
Download-URL: https://github.com/kapot65/random_custom_pdf/tarball/0.0.1master.zip
Platform: any
